maple/__init__.py
maple/py.typed
maple/adapters/a2a_adapter.py
maple/adapters/acp_adapter.py
maple/adapters/autogen_adapter.py
maple/adapters/crewai_adapter.py
maple/adapters/fipa_acl_adapter.py
maple/adapters/langgraph_adapter.py
maple/adapters/mcp_adapter.py
maple/adapters/openai_sdk_adapter.py
maple/agent/__init__.py
maple/agent/agent.py
maple/agent/config.py
maple/agent/handlers.py
maple/broker/__init__.py
maple/broker/broker.py
maple/broker/nats_broker.py
maple/broker/production_broker.py
maple/broker/queue.py
maple/broker/routing.py
maple/communication/__init__.py
maple/communication/pubsub.py
maple/communication/request_response.py
maple/communication/streaming.py
maple/core/__init__.py
maple/core/message.py
maple/core/result.py
maple/core/serialization.py
maple/core/types.py
maple/discovery/__init__.py
maple/discovery/capability_matcher.py
maple/discovery/failure_detector.py
maple/discovery/health_monitor.py
maple/discovery/registry.py
maple/error/__init__.py
maple/error/circuit_breaker.py
maple/error/recovery.py
maple/error/types.py
maple/monitoring/__init__.py
maple/monitoring/health_monitor.py
maple/resources/__init__.py
maple/resources/manager.py
maple/resources/negotiation.py
maple/resources/specification.py
maple/security/__init__.py
maple/security/audit.py
maple/security/authentication.py
maple/security/authorization.py
maple/security/cryptography_impl.py
maple/security/encryption.py
maple/security/link.py
maple/state/__init__.py
maple/state/consistency.py
maple/state/store.py
maple/state/synchronization.py
maple/task_management/__init__.py
maple/task_management/fault_tolerance.py
maple/task_management/monitor.py
maple/task_management/performance_optimizer.py
maple/task_management/result_collector.py
maple/task_management/scheduler.py
maple/task_management/task_queue.py
maple_oss-1.0.1.dist-info/licenses/LICENSE
maple_oss-1.0.1.dist-info/METADATA
maple_oss-1.0.1.dist-info/WHEEL
maple_oss-1.0.1.dist-info/entry_points.txt
maple_oss-1.0.1.dist-info/top_level.txt
maple_oss-1.0.1.dist-info/RECORD
