Metadata-Version: 2.4
Name: maple-oss
Version: 1.0.1
Summary: Multi Agent Protocol Language Engine - Advanced Multi-Agent Communication Protocol Framework
Home-page: https://github.com/maheshvaikri-code/maple-oss
Author: Mahesh Vaijainthymala Krishnamoorthy
Author-email: Mahesh Vaijainthymala Krishnamoorthy <mahesh@mapleagent.org>
Maintainer: Mahesh Vaikri
Maintainer-email: Mahesh Vaikri <mahesh@mapleagent.org>
License: AGPL-3.0
Project-URL: Homepage, https://github.com/maheshvaikri-code/maple-oss
Project-URL: Documentation, https://mapleagent.org/docs
Project-URL: Repository, https://github.com/maheshvaikri-code/maple-oss
Project-URL: Issues, https://github.com/maheshvaikri-code/maple-oss/issues
Project-URL: Discussions, https://github.com/maheshvaikri-code/maple-oss/discussions
Project-URL: Changelog, https://github.com/maheshvaikri-code/maple-oss/CHANGELOG.md
Keywords: multi-agent,agent-communication,distributed-systems,ai-agents,protocol,maple,automation,resource-management,error-handling,security
Classifier: Development Status :: 5 - Production/Stable
Classifier: Intended Audience :: Developers
Classifier: Intended Audience :: Science/Research
Classifier: License :: OSI Approved :: GNU Affero General Public License v3
Classifier: Operating System :: OS Independent
Classifier: Programming Language :: Python :: 3
Classifier: Programming Language :: Python :: 3.8
Classifier: Programming Language :: Python :: 3.9
Classifier: Programming Language :: Python :: 3.10
Classifier: Programming Language :: Python :: 3.11
Classifier: Programming Language :: Python :: 3.12
Classifier: Topic :: Software Development :: Libraries :: Python Modules
Classifier: Topic :: System :: Distributed Computing
Classifier: Topic :: Scientific/Engineering :: Artificial Intelligence
Classifier: Topic :: Internet :: WWW/HTTP :: HTTP Servers
Classifier: Topic :: System :: Networking
Requires-Python: >=3.8
License-File: LICENSE
Requires-Dist: asyncio-mqtt>=0.11.0
Requires-Dist: cryptography>=41.0.0
Requires-Dist: websockets>=11.0.0
Requires-Dist: pydantic>=2.0.0
Requires-Dist: python-dateutil>=2.8.0
Requires-Dist: typing-extensions>=4.0.0; python_version < "3.10"
Provides-Extra: dev
Requires-Dist: pytest>=7.0.0; extra == "dev"
Requires-Dist: pytest-asyncio>=0.21.0; extra == "dev"
Requires-Dist: pytest-cov>=4.0.0; extra == "dev"
Requires-Dist: black>=23.0.0; extra == "dev"
Requires-Dist: flake8>=6.0.0; extra == "dev"
Requires-Dist: mypy>=1.0.0; extra == "dev"
Requires-Dist: isort>=5.12.0; extra == "dev"
Requires-Dist: bandit>=1.7.0; extra == "dev"
Requires-Dist: pre-commit>=3.0.0; extra == "dev"
Provides-Extra: docs
Requires-Dist: sphinx>=6.0.0; extra == "docs"
Requires-Dist: sphinx-rtd-theme>=1.3.0; extra == "docs"
Requires-Dist: myst-parser>=2.0.0; extra == "docs"
Provides-Extra: performance
Requires-Dist: uvloop>=0.17.0; platform_system != "Windows" and extra == "performance"
Requires-Dist: orjson>=3.8.0; extra == "performance"
Requires-Dist: msgpack>=1.0.0; extra == "performance"
Provides-Extra: security
Requires-Dist: cryptography[ssh]>=41.0.0; extra == "security"
Requires-Dist: pyjwt>=2.8.0; extra == "security"
Dynamic: author
Dynamic: home-page
Dynamic: license-file
Dynamic: maintainer
Dynamic: requires-python
